mumu/__init__.py
mumu/_version.py
mumu/automl/__init__.py
mumu/commands/__init__.py
mumu/conf/__init__.py
mumu/conf/_read_cfg.py
mumu/conf/_write_cfg.py
mumu/crawler/__init__.py
mumu/db/__init__.py
mumu/db/_check.py
mumu/db/_hive.py
mumu/db/_impala.py
mumu/db/_mysql.py
mumu/db/_redis.py
mumu/decorators/__init__.py
mumu/decorators/_progressbar.py
mumu/decorators/_retry.py
mumu/decorators/_timeit.py
mumu/feature/__init__.py
mumu/feature/_contingency.py
mumu/feature/_eda.py
mumu/feature/_psi.py
mumu/feature/_woe.py
mumu/io/__init__.py
mumu/magics/__init__.py
mumu/mail/__init__.py
mumu/model/__init__.py
mumu/model/_evaluate.py
mumu/model/_lightgbm.py
mumu/model/_xgboost.py
mumu/monitor/__init__.py
mumu/plots/__init__.py
mumu/robots/__init__.py
mumu/robots/_workwx.py
mumu/tests/__init__.py
mumu/utils/__init__.py
mumu/utils/_pandas.py
mumu/web/__init__.py
mumu-0.0.8.dist-info/LICENSE
mumu-0.0.8.dist-info/METADATA
mumu-0.0.8.dist-info/WHEEL
mumu-0.0.8.dist-info/top_level.txt
mumu-0.0.8.dist-info/RECORD
