Metadata-Version: 2.1
Name: mumu
Version: 0.0.8
Summary: mumu is an integrated tool for machine learning.
Home-page: https://github.com/mingminyu/mumu
Author: yumingmin
Author-email: yu_mingm623@163.com
Maintainer: yumingmin
Maintainer-email: yu_mingm623@163.com
License: Apache License, Version 2.0
Keywords: machine-learning python impala hive sql monitoremail airflow
Platform: all
Classifier: Programming Language :: Python :: 3.6
Classifier: Programming Language :: Python :: 3.7
Classifier: Programming Language :: Python :: 3.8
Classifier: Programming Language :: Python :: 3.9
License-File: LICENSE
Requires-Dist: impyla
Requires-Dist: requests
